rest_framework_datatables/__init__.py
rest_framework_datatables/filters.py
rest_framework_datatables/pagination.py
rest_framework_datatables/renderers.py
rest_framework_datatables/utils.py
rest_framework_datatables/django_filters/__init__.py
rest_framework_datatables/django_filters/backends.py
rest_framework_datatables/django_filters/filters.py
rest_framework_datatables/django_filters/filterset.py
djangorestframework_datatables-0.7.2.dist-info/LICENSE
djangorestframework_datatables-0.7.2.dist-info/METADATA
djangorestframework_datatables-0.7.2.dist-info/WHEEL
djangorestframework_datatables-0.7.2.dist-info/top_level.txt
djangorestframework_datatables-0.7.2.dist-info/RECORD
